dotdotfarm/__init__.py
dotdotfarm/dotdotweb.py
dotdotfarm/callbacks/__init__.py
dotdotfarm/callbacks/callbacks.py
dotdotfarm/callbacks/cobject.py
dotdotfarm/engines/__init__.py
dotdotfarm/engines/http_engine.py
dotdotfarm/engines/websock_engine.py
dotdotfarm/generators/__init__.py
dotdotfarm/generators/words_generator.py
dotdotfarm-1.6.0.dist-info/LICENSE
dotdotfarm-1.6.0.dist-info/METADATA
dotdotfarm-1.6.0.dist-info/WHEEL
dotdotfarm-1.6.0.dist-info/entry_points.txt
dotdotfarm-1.6.0.dist-info/top_level.txt
dotdotfarm-1.6.0.dist-info/RECORD
