Metadata-Version: 2.1
Name: dotdotfarm
Version: 1.6.0
Summary: Path Traversal exploitation tool
Author: treddis
License: GPL
License-File: LICENSE
Requires-Dist: aiohttp ==3.8.4
Requires-Dist: colorama ==0.4.6
Requires-Dist: setuptools ==66.1.1
Requires-Dist: tqdm ==4.64.1
Requires-Dist: yarl ==1.8.2
Requires-Dist: multidict ==6.0.4
Requires-Dist: attrs ==22.2.0
Requires-Dist: async-timeout ==4.0.2
Requires-Dist: aiosignal ==1.3.1
